{"cameraMode":{"drawMode":0,"name":"Shaded","section":"Shading Mode"},"sceneLighting":false,"audioPlay":false,"sceneViewState":{"showFog":true,"showMaterialUpdate":false,"showSkybox":false,"showFlares":true,"showImageEffects":true,"showParticleSystems":true},"in2DMode":false,"pivot":{"x":-0.045068979263305667,"y":0.9406293630599976,"z":0.04571563005447388},"rotation":{"x":0.10224305838346482,"y":0.881077229976654,"z":-0.2226293385028839,"w":0.40461230278015139},"size":1.5899173021316529,"orthographic":false}